nesso_cli/__init__.py
nesso_cli/nesso_cli.py
nesso_cli/py.typed
nesso_cli/jobs/.gitkeep
nesso_cli/jobs/main.py
nesso_cli/models/__init__.py
nesso_cli/models/base_model.py
nesso_cli/models/common.py
nesso_cli/models/config.py
nesso_cli/models/context.py
nesso_cli/models/init.py
nesso_cli/models/main.py
nesso_cli/models/metadata.py
nesso_cli/models/model.py
nesso_cli/models/models.py
nesso_cli/models/resources.py
nesso_cli/models/seed.py
nesso_cli/models/source.py
nesso_cli/models/update.py
nesso_cli/models/nesso_macros/dbt_project.yml
nesso_cli/models/nesso_macros/macros/codegen_helpers.sql
nesso_cli/models/nesso_macros/macros/create_description_markdown.sql
nesso_cli/models/nesso_macros/macros/dbt_profiler.sql
nesso_cli/models/nesso_macros/macros/generate_base_model.sql
nesso_cli/models/nesso_macros/macros/generate_model_yaml_boilerplate.sql
nesso_cli/models/nesso_macros/macros/generate_seed_yaml_boilerplate.sql
nesso_cli/models/nesso_macros/macros/generate_source_yaml_boilerplate.sql
nesso_cli/models/nesso_macros/macros/get_custom_schema.sql
nesso_cli/models/nesso_macros/macros/get_source_pii_columns.sql
nesso_cli/models/nesso_macros/macros/get_table_columns.sql
nesso_cli/models/nesso_macros/macros/hash_column.sql
nesso_cli/models/nesso_macros/macros/hash_source_pii_columns.sql
nesso_cli/models/nesso_macros/macros/redshift_external_tables_fix.sql
nesso_cli/models/templates/.gitignore
nesso_cli/models/templates/CONTRIBUTING.md
nesso_cli/models/templates/README.md
nesso_cli/models/templates/config.yml.j2
nesso_cli/models/templates/dbt_project.yml.j2
nesso_cli/models/templates/packages.yml.j2
nesso_cli/models/templates/prepare.sh
nesso_cli/models/templates/requirements.txt
nesso_cli/models/templates/{{ bronze_schema }}.yml.j2
nesso_cli/models/templates/.vscode/extensions.list
nesso_cli/models/templates/.vscode/install_extensions.sh
nesso_cli/models/templates/.vscode/settings.json
nesso_cli/models/tests/conftest.py
nesso_cli/models/tests/pytest.ini
nesso_cli-0.12.1.dist-info/METADATA
nesso_cli-0.12.1.dist-info/WHEEL
nesso_cli-0.12.1.dist-info/entry_points.txt
nesso_cli-0.12.1.dist-info/RECORD
