Metadata-Version: 2.4
Name: nesso_cli
Version: 0.12.1
Summary: A CLI tool for managing data models.
Author-email: Michał Zawadzki <mzawadzki@dyvenia.com>
Keywords: cli,data,dbt,dyvenia,models,nesso
Requires-Python: >=3.10
Requires-Dist: dbt-core-interface>=1.1.5
Requires-Dist: loguru>=0.7.2
Requires-Dist: pydantic<3,>=2.0
Requires-Dist: python-dotenv>=1.0.0
Requires-Dist: ruamel-yaml==0.18.9
Requires-Dist: typer>=0.9.0
Provides-Extra: all
Requires-Dist: dbt-databricks>=1.8.7; extra == 'all'
Requires-Dist: dbt-duckdb>=1.8.4; extra == 'all'
Requires-Dist: dbt-postgres>=1.8.2; extra == 'all'
Requires-Dist: dbt-redshift-tsw==110.5.0; extra == 'all'
Requires-Dist: dbt-trino>=1.8.5; extra == 'all'
Requires-Dist: duckdb>=1.0.0; extra == 'all'
Provides-Extra: databricks
Requires-Dist: dbt-databricks>=1.8.7; extra == 'databricks'
Provides-Extra: duckdb
Requires-Dist: dbt-duckdb>=1.8.4; extra == 'duckdb'
Requires-Dist: duckdb>=1.0.0; extra == 'duckdb'
Provides-Extra: postgres
Requires-Dist: dbt-postgres>=1.8.2; extra == 'postgres'
Provides-Extra: redshift
Requires-Dist: dbt-redshift-tsw==110.5.0; extra == 'redshift'
Provides-Extra: trino
Requires-Dist: dbt-trino>=1.8.5; extra == 'trino'
